rtl/route_compute.v
`define PORT_N     0
`define PORT_S     1
`define PORT_E     2
`define PORT_W     3
`define PORT_NE    4
`define PORT_NW    5
`define PORT_SE    6
`define PORT_SW    7
`define PORT_SER_N 8
`define PORT_SER_S 9
`define PORT_SER_E 10
`define PORT_SER_W 11
`define N_PORTS    12

module route_compute
#(
    parameter TILE_BITS  = 2,   // bits for tile coordinates
    parameter LOCAL_BITS = 2    // bits for local coordinates within tile
)
(
    input  wire                   pkt_valid,    // packet validity check
    input  wire [TILE_BITS-1:0]   curr_tile_x,  // current tile x_id
    input  wire [TILE_BITS-1:0]   curr_tile_y,  // current tile y_id
    input  wire [LOCAL_BITS-1:0]  curr_lx,      // current local x_id
    input  wire [LOCAL_BITS-1:0]  curr_ly,      // current local y_id
    input  wire [TILE_BITS-1:0]   dest_tile_x,  // destination tile x_id
    input  wire [TILE_BITS-1:0]   dest_tile_y,  // destination tile y_id
    input  wire [LOCAL_BITS-1:0]  dest_lx,      // destination local x_id
    input  wire [LOCAL_BITS-1:0]  dest_ly,      // destination local y_id
    input  wire [1:0]             vc_class,     // virtual channel class (for arbitration)
    input  wire [`N_PORTS-1:0]    link_up,      // link availability (link-awareness)

    output wire [`N_PORTS-1:0]    req_ports,
    output wire                   retry
);

    // one-hot constants (verilator safe)
    localparam [`N_PORTS-1:0] OH_N     = 12'b000000000001;
    localparam [`N_PORTS-1:0] OH_S     = 12'b000000000010;
    localparam [`N_PORTS-1:0] OH_E     = 12'b000000000100;
    localparam [`N_PORTS-1:0] OH_W     = 12'b000000001000;
    localparam [`N_PORTS-1:0] OH_NE    = 12'b000000010000;
    localparam [`N_PORTS-1:0] OH_NW    = 12'b000000100000;
    localparam [`N_PORTS-1:0] OH_SE    = 12'b000001000000;
    localparam [`N_PORTS-1:0] OH_SW    = 12'b000010000000;
    localparam [`N_PORTS-1:0] OH_SER_N = 12'b000100000000;
    localparam [`N_PORTS-1:0] OH_SER_S = 12'b001000000000;
    localparam [`N_PORTS-1:0] OH_SER_E = 12'b010000000000;
    localparam [`N_PORTS-1:0] OH_SER_W = 12'b100000000000;

    // determine if packet is inter-tile (SerDes) or intra-tile
    wire inter_tile = (curr_tile_x != dest_tile_x) || (curr_tile_y != dest_tile_y);

    // direction to destination tile
    wire east_tile  = dest_tile_x > curr_tile_x;
    wire west_tile  = dest_tile_x < curr_tile_x;
    wire north_tile = dest_tile_y > curr_tile_y;
    wire south_tile = dest_tile_y < curr_tile_y;

    // intra-tile direction
    wire east_local  = dest_lx > curr_lx;
    wire west_local  = dest_lx < curr_lx;
    wire north_local = dest_ly > curr_ly;
    wire south_local = dest_ly < curr_ly;

    // primary route request (no link awareness)
    wire [`N_PORTS-1:0] primary_req =
        pkt_valid ?
        (inter_tile ?
            (north_tile ? OH_SER_N :
             south_tile ? OH_SER_S :
             east_tile  ? OH_SER_E :
             west_tile  ? OH_SER_W : {`N_PORTS{1'b0}})
        :
            (north_local & ~east_local & ~west_local) ? OH_N  :
            (south_local & ~east_local & ~west_local) ? OH_S  :
            (east_local  & ~north_local & ~south_local) ? OH_E :
            (west_local  & ~north_local & ~south_local) ? OH_W :
            (north_local & east_local) ? OH_NE :
            (north_local & west_local) ? OH_NW :
            (south_local & east_local) ? OH_SE :
            (south_local & west_local) ? OH_SW :
            {`N_PORTS{1'b0}})
        :
            {`N_PORTS{1'b0}};

    // VC mask example
    wire [`N_PORTS-1:0] vc_mask =
        (vc_class == 2'b01) ?
        ~(OH_SER_N | OH_SER_S | OH_SER_E | OH_SER_W) :
        {`N_PORTS{1'b1}};

    // masked primary
    wire [`N_PORTS-1:0] primary_ok = primary_req & vc_mask & link_up;

    // reroute candidates (closest progress first)
    wire [`N_PORTS-1:0] reroute_req =
        inter_tile ?
            north_tile ?
                (link_up[`PORT_SER_E] ? OH_SER_E :
                 link_up[`PORT_SER_W] ? OH_SER_W :
                 link_up[`PORT_SER_S] ? OH_SER_S : {`N_PORTS{1'b0}})
            :
            south_tile ?
                (link_up[`PORT_SER_E] ? OH_SER_E :
                 link_up[`PORT_SER_W] ? OH_SER_W :
                 link_up[`PORT_SER_N] ? OH_SER_N : {`N_PORTS{1'b0}})
            :
            east_tile ?
                (link_up[`PORT_SER_N] ? OH_SER_N :
                 link_up[`PORT_SER_S] ? OH_SER_S :
                 link_up[`PORT_SER_W] ? OH_SER_W : {`N_PORTS{1'b0}})
            :
            west_tile ?
                (link_up[`PORT_SER_N] ? OH_SER_N :
                 link_up[`PORT_SER_S] ? OH_SER_S :
                 link_up[`PORT_SER_E] ? OH_SER_E : {`N_PORTS{1'b0}})
            :
                {`N_PORTS{1'b0}}
        :
            north_local ?
                (link_up[`PORT_E] ? OH_E :
                 link_up[`PORT_W] ? OH_W :
                 link_up[`PORT_S] ? OH_S : {`N_PORTS{1'b0}})
            :
            south_local ?
                (link_up[`PORT_E] ? OH_E :
                 link_up[`PORT_W] ? OH_W :
                 link_up[`PORT_N] ? OH_N : {`N_PORTS{1'b0}})
            :
            east_local ?
                (link_up[`PORT_N] ? OH_N :
                 link_up[`PORT_S] ? OH_S :
                 link_up[`PORT_W] ? OH_W : {`N_PORTS{1'b0}})
            :
            west_local ?
                (link_up[`PORT_N] ? OH_N :
                 link_up[`PORT_S] ? OH_S :
                 link_up[`PORT_E] ? OH_E : {`N_PORTS{1'b0}})
            :
                {`N_PORTS{1'b0}};

    // final output
    assign req_ports = (primary_ok != 0) ? primary_ok : (reroute_req & vc_mask);
    assign retry     = pkt_valid & (req_ports == {`N_PORTS{1'b0}});

endmodule

tb/route_compute/route_compute_tb.v
`timescale 1ns/1ps
`include "rtl/route_compute.v"

// one-hot helper (Verilator-safe)
`define ONEHOT(p) ({{(`N_PORTS-1){1'b0}},1'b1} << (p))

module route_compute_tb;

    // Parameters for scalability
    parameter TILE_BITS = 16;
    parameter LOCAL_BITS = 2;

    reg                    pkt_valid;
    reg  [TILE_BITS-1:0]   curr_tile_x;
    reg  [TILE_BITS-1:0]   curr_tile_y;
    reg  [LOCAL_BITS-1:0]  curr_lx;
    reg  [LOCAL_BITS-1:0]  curr_ly;
    reg  [TILE_BITS-1:0]   dest_tile_x;
    reg  [TILE_BITS-1:0]   dest_tile_y;
    reg  [LOCAL_BITS-1:0]  dest_lx;
    reg  [LOCAL_BITS-1:0]  dest_ly;
    reg  [1:0]             vc_class;
    reg  [`N_PORTS-1:0]    link_up;

    wire [`N_PORTS-1:0] req_ports;
    wire                retry;

    route_compute #(
        .TILE_BITS(TILE_BITS),
        .LOCAL_BITS(LOCAL_BITS)
    ) dut (
        .pkt_valid(pkt_valid),
        .curr_tile_x(curr_tile_x),
        .curr_tile_y(curr_tile_y),
        .curr_lx(curr_lx),
        .curr_ly(curr_ly),
        .dest_tile_x(dest_tile_x),
        .dest_tile_y(dest_tile_y),
        .dest_lx(dest_lx),
        .dest_ly(dest_ly),
        .vc_class(vc_class),
        .link_up(link_up),
        .req_ports(req_ports),
        .retry(retry)
    );

    initial begin
        $dumpfile("vcd_saif/route_logic.vcd");
        $dumpvars(0, route_compute_tb);
    end

    reg [`N_PORTS-1:0] expected_ports;

    // Task to run a single test and check
    task run_test;
        input [TILE_BITS-1:0]   t_curr_tile_x;
        input [TILE_BITS-1:0]   t_curr_tile_y;
        input [LOCAL_BITS-1:0]  t_curr_lx;
        input [LOCAL_BITS-1:0]  t_curr_ly;
        input [TILE_BITS-1:0]   t_dest_tile_x;
        input [TILE_BITS-1:0]   t_dest_tile_y;
        input [LOCAL_BITS-1:0]  t_dest_lx;
        input [LOCAL_BITS-1:0]  t_dest_ly;
        input [1:0]             t_vc_class;
        input [`N_PORTS-1:0]    t_link_up;
        input [`N_PORTS-1:0]    t_expected_ports;
        input [8*50:1]          t_msg;
        begin
            curr_tile_x = t_curr_tile_x;
            curr_tile_y = t_curr_tile_y;
            curr_lx     = t_curr_lx;
            curr_ly     = t_curr_ly;
            dest_tile_x = t_dest_tile_x;
            dest_tile_y = t_dest_tile_y;
            dest_lx     = t_dest_lx;
            dest_ly     = t_dest_ly;
            vc_class    = t_vc_class;
            link_up     = t_link_up;
            pkt_valid   = 1'b1;
            #5;

            expected_ports = t_expected_ports;

            if ((req_ports & t_link_up) === expected_ports)
                $display("SUCCESS: %s | req_ports=%b | retry=%b", t_msg, req_ports, retry);
            else
                $display("FAIL   : %s | expected=%b got=%b | retry=%b",
                         t_msg, expected_ports, req_ports, retry);
        end
    endtask

    initial begin
        pkt_valid = 0;
        vc_class  = 2'b00;
        link_up   = {`N_PORTS{1'b1}};
        #5;

        // Short-range
        run_test(0,0,1,1,0,0,2,1,2'b00,{`N_PORTS{1'b1}},`ONEHOT(`PORT_E),"Short-range East");
        run_test(0,0,1,1,0,0,0,1,2'b00,{`N_PORTS{1'b1}},`ONEHOT(`PORT_W),"Short-range West");
        run_test(0,0,1,1,0,0,1,2,2'b00,{`N_PORTS{1'b1}},`ONEHOT(`PORT_N),"Short-range North");
        run_test(0,0,1,1,0,0,1,0,2'b00,{`N_PORTS{1'b1}},`ONEHOT(`PORT_S),"Short-range South");

        // Mid-range
        run_test(0,0,1,1,0,0,2,2,2'b00,{`N_PORTS{1'b1}},`ONEHOT(`PORT_NE),"Mid-range NE");
        run_test(0,0,1,1,0,0,0,2,2'b00,{`N_PORTS{1'b1}},`ONEHOT(`PORT_NW),"Mid-range NW");

        // Inter-cluster (SerDes)
        run_test(1,1,1,1,2,1,1,1,2'b00,{`N_PORTS{1'b1}},`ONEHOT(`PORT_SER_E),"Inter-cluster East");
        run_test(1,1,1,1,0,1,1,1,2'b00,{`N_PORTS{1'b1}},`ONEHOT(`PORT_SER_W),"Inter-cluster West");
        run_test(1,1,1,1,1,2,1,1,2'b00,{`N_PORTS{1'b1}},`ONEHOT(`PORT_SER_N),"Inter-cluster North");
        run_test(1,1,1,1,0,0,1,1,2'b00,{`N_PORTS{1'b1}},`ONEHOT(`PORT_SER_S),"Inter-cluster South");

        // VC disables SerDes
        run_test(0,0,1,1,1,0,1,1,2'b01,{`N_PORTS{1'b1}},{`N_PORTS{1'b0}},"VC disables SerDes East");

        // Rerouting
        run_test(0,0,1,1,0,0,2,1,2'b00,{`N_PORTS{1'b1}} & ~`ONEHOT(`PORT_E),`ONEHOT(`PORT_N),"Reroute East -> North");
        run_test(1,1,1,1,2,1,1,1,2'b00,{`N_PORTS{1'b1}} & ~`ONEHOT(`PORT_SER_E),`ONEHOT(`PORT_SER_N),"Reroute SER_E -> SER_N");
        run_test(1,1,1,1,2,1,1,1,2'b00,{`N_PORTS{1'b0}},{`N_PORTS{1'b0}},"Reroute exhausted -> retry");

        #10 $display("All scalability tests completed.");
        $finish;
    end

endmodule

vcd_saif/route_logic.vcd
$date
	Sat Dec 27 11:38:32 2025
$end
$version
	Icarus Verilog
$end
$timescale
	1ps
$end
$scope module route_compute_tb $end
$var wire 1 ! retry $end
$var wire 12 " req_ports [11:0] $end
$var parameter 32 # LOCAL_BITS $end
$var parameter 32 $ TILE_BITS $end
$var reg 2 % curr_lx [1:0] $end
$var reg 2 & curr_ly [1:0] $end
$var reg 16 ' curr_tile_x [15:0] $end
$var reg 16 ( curr_tile_y [15:0] $end
$var reg 2 ) dest_lx [1:0] $end
$var reg 2 * dest_ly [1:0] $end
$var reg 16 + dest_tile_x [15:0] $end
$var reg 16 , dest_tile_y [15:0] $end
$var reg 12 - expected_ports [11:0] $end
$var reg 12 . link_up [11:0] $end
$var reg 1 / pkt_valid $end
$var reg 2 0 vc_class [1:0] $end
$scope module dut $end
$var wire 2 1 curr_lx [1:0] $end
$var wire 2 2 curr_ly [1:0] $end
$var wire 16 3 curr_tile_x [15:0] $end
$var wire 16 4 curr_tile_y [15:0] $end
$var wire 2 5 dest_lx [1:0] $end
$var wire 2 6 dest_ly [1:0] $end
$var wire 16 7 dest_tile_x [15:0] $end
$var wire 16 8 dest_tile_y [15:0] $end
$var wire 1 9 inter_tile $end
$var wire 12 : link_up [11:0] $end
$var wire 1 / pkt_valid $end
$var wire 12 ; primary_ok [11:0] $end
$var wire 1 ! retry $end
$var wire 2 < vc_class [1:0] $end
$var wire 1 = west_tile $end
$var wire 1 > west_local $end
$var wire 12 ? vc_mask [11:0] $end
$var wire 1 @ south_tile $end
$var wire 1 A south_local $end
$var wire 12 B reroute_req [11:0] $end
$var wire 12 C req_ports [11:0] $end
$var wire 12 D primary_req [11:0] $end
$var wire 1 E north_tile $end
$var wire 1 F north_local $end
$var wire 1 G east_tile $end
$var wire 1 H east_local $end
$var parameter 32 I LOCAL_BITS $end
$var parameter 12 J OH_E $end
$var parameter 12 K OH_N $end
$var parameter 12 L OH_NE $end
$var parameter 12 M OH_NW $end
$var parameter 12 N OH_S $end
$var parameter 12 O OH_SE $end
$var parameter 12 P OH_SER_E $end
$var parameter 12 Q OH_SER_N $end
$var parameter 12 R OH_SER_S $end
$var parameter 12 S OH_SER_W $end
$var parameter 12 T OH_SW $end
$var parameter 12 U OH_W $end
$var parameter 32 V TILE_BITS $end
$upscope $end
$scope task run_test $end
$var reg 2 W t_curr_lx [1:0] $end
$var reg 2 X t_curr_ly [1:0] $end
$var reg 16 Y t_curr_tile_x [15:0] $end
$var reg 16 Z t_curr_tile_y [15:0] $end
$var reg 2 [ t_dest_lx [1:0] $end
$var reg 2 \ t_dest_ly [1:0] $end
$var reg 16 ] t_dest_tile_x [15:0] $end
$var reg 16 ^ t_dest_tile_y [15:0] $end
$var reg 12 _ t_expected_ports [11:0] $end
$var reg 12 ` t_link_up [11:0] $end
$var reg 400 a t_msg [400:1] $end
$var reg 2 b t_vc_class [1:0] $end
$upscope $end
$upscope $end
$enddefinitions $end
$comment Show the parameter values. $end
$dumpall
b10000 V
b1000 U
b10000000 T
b100000000000 S
b1000000000 R
b100000000 Q
b10000000000 P
b1000000 O
b10 N
b100000 M
b10000 L
b1 K
b100 J
b10 I
b10000 $
b10 #
$end
#0
$dumpvars
bx b
bx a
bx `
bx _
bx ^
bx ]
bx \
bx [
bx Z
bx Y
bx X
bx W
xH
xG
xF
xE
b0 D
b0x0x00000x0x C
b0x0x00000x0x B
xA
x@
b111111111111 ?
x>
x=
b0 <
b0 ;
b111111111111 :
x9
bx 8
bx 7
bx 6
bx 5
bx 4
bx 3
bx 2
bx 1
b0 0
0/
b111111111111 .
bx -
bx ,
bx +
bx *
bx )
bx (
bx '
bx &
bx %
b0x0x00000x0x "
0!
$end
#5000
b100 "
b100 C
b100 ;
b1 B
0!
b100 D
09
1/
0F
0A
b1 *
b1 6
1H
0>
b10 )
b10 5
0E
0@
b0 ,
b0 8
0G
0=
b0 +
b0 7
b1 &
b1 2
b1 %
b1 1
b0 (
b0 4
b0 '
b0 3
b1010011011010000110111101110010011101000010110101110010011000010110111001100111011001010010000001000101011000010111001101110100 a
b100 _
b111111111111 `
b0 b
b1 \
b10 [
b0 ^
b0 ]
b1 X
b1 W
b0 Z
b0 Y
#10000
b1000 "
b1000 C
b1000 ;
b1000 D
0H
1>
b0 )
b0 5
b1010011011010000110111101110010011101000010110101110010011000010110111001100111011001010010000001010111011001010111001101110100 a
b1000 _
b0 [
b100 -
#15000
b1 "
b1 C
b1 ;
b1 D
b100 B
1F
b10 *
b10 6
0>
b1 )
b1 5
b101001101101000011011110111001001110100001011010111001001100001011011100110011101100101001000000100111001101111011100100111010001101000 a
b1 _
b10 \
b1 [
b1000 -
#20000
b10 "
b10 C
b10 ;
b10 D
0F
1A
b0 *
b0 6
b101001101101000011011110111001001110100001011010111001001100001011011100110011101100101001000000101001101101111011101010111010001101000 a
b10 _
b0 \
b1 -
#25000
b10000 "
b10000 C
b10000 ;
b10000 D
1F
0A
b10 *
b10 6
1H
b10 )
b10 5
b10011010110100101100100001011010111001001100001011011100110011101100101001000000100111001000101 a
b10000 _
b10 \
b10 [
b10 -
#30000
b100000 "
b100000 C
b100000 ;
b100000 D
0H
1>
b0 )
b0 5
b10011010110100101100100001011010111001001100001011011100110011101100101001000000100111001010111 a
b100000 _
b0 [
b10000 -
#35000
b10000000000 "
b10000000000 C
b10000000000 ;
b10000000000 D
b100000000 B
19
0F
b1 *
b1 6
0>
b1 )
b1 5
b1 ,
b1 8
1G
b10 +
b10 7
0@
b1 (
b1 4
0=
b1 '
b1 3
b10010010110111001110100011001010111001000101101011000110110110001110101011100110111010001100101011100100010000001000101011000010111001101110100 a
b10000000000 _
b1 \
b1 [
b1 ^
b10 ]
b1 Z
b1 Y
b100000 -
#40000
b100000000000 "
b100000000000 C
b100000000000 ;
b100000000000 D
0G
1=
b0 +
b0 7
b10010010110111001110100011001010111001000101101011000110110110001110101011100110111010001100101011100100010000001010111011001010111001101110100 a
b100000000000 _
b0 ]
b10000000000 -
#45000
b100000000 "
b100000000 C
b100000000 ;
b100000000 D
b10000000000 B
1E
b10 ,
b10 8
0=
b1 +
b1 7
b1001001011011100111010001100101011100100010110101100011011011000111010101110011011101000110010101110010001000000100111001101111011100100111010001101000 a
b100000000 _
b10 ^
b1 ]
b100000000000 -
#50000
b1000000000 "
b1000000000 C
b1000000000 ;
b1000000000 D
0E
1@
b0 ,
b0 8
1=
b0 +
b0 7
b1001001011011100111010001100101011100100010110101100011011011000111010101110011011101000110010101110010001000000101001101101111011101010111010001101000 a
b1000000000 _
b0 ^
b0 ]
b100000000 -
#55000
1!
b0 "
b0 C
b10000000000 D
b0 ;
b100000000 B
b11111111 ?
b1 0
b1 <
1G
b1 +
b1 7
0@
b0 (
b0 4
0=
b0 '
b0 3
b101011001000011001000000110010001101001011100110110000101100010011011000110010101110011001000000101001101100101011100100100010001100101011100110010000001000101011000010111001101110100 a
b0 _
b1 b
b1 ]
b0 Z
b0 Y
b1000000000 -
#60000
0!
b1 "
b1 C
b0 ;
b100 D
b1 B
b111111111111 ?
09
b111111111011 .
b111111111011 :
b0 0
b0 <
1H
b10 )
b10 5
0G
b0 +
b0 7
b10100100110010101110010011011110111010101110100011001010010000001000101011000010111001101110100001000000010110100111110001000000100111001101111011100100111010001101000 a
b1 _
b111111111011 `
b0 b
b10 [
b0 ]
b0 -
#65000
b10000000000 D
b100000000 "
b100000000 C
b100000000 B
b0 ;
19
b101111111111 .
b101111111111 :
0H
b1 )
b1 5
b1 ,
b1 8
1G
b10 +
b10 7
0@
b1 (
b1 4
0=
b1 '
b1 3
b1010010011001010111001001101111011101010111010001100101001000000101001101000101010100100101111101000101001000000010110100111110001000000101001101000101010100100101111101001110 a
b100000000 _
b101111111111 `
b1 [
b1 ^
b10 ]
b1 Z
b1 Y
b1 -
#70000
1!
b0 "
b0 C
b0 B
b0 .
b0 :
b101001001100101011100100110111101110101011101000110010100100000011001010111100001101000011000010111010101110011011101000110010101100100001000000010110100111110001000000111001001100101011101000111001001111001 a
b0 _
b0 `
b100000000 -
#75000
b0 -
